backup_podcasts/__init__.py
backup_podcasts/__main__.py
backup_podcasts/backup_dharmatalks.py
backup_podcasts/backup_podcasts.py
backup_podcasts/test.py
LICENSE
backup_podcasts-0.2.dist-info/LICENSE
backup_podcasts-0.2.dist-info/METADATA
backup_podcasts-0.2.dist-info/WHEEL
backup_podcasts-0.2.dist-info/RECORD
